{
  "type": "minecraft:crafting_shapeless",
  "ingredients": [
    {
      "item": "doggytalents:wool_collar"
    },
    {
      "item": "minecraft:string"
    },
    {
      "item": "minecraft:blue_dye"
    },
    {
      "item": "minecraft:lime_dye"
    },
    {
      "item": "minecraft:yellow_dye"
    },
    {
      "item": "minecraft:orange_dye"
    },
    {
      "item": "minecraft:red_dye"
    },
    {
      "item": "minecraft:purple_dye"
    }
  ],
  "result": {
    "item": "doggytalents:multicoloured_collar"
  }
}